optimum/graphcore/__init__.py
optimum/graphcore/ipu_configuration.py
optimum/graphcore/modelcard.py
optimum/graphcore/modeling_utils.py
optimum/graphcore/trainer.py
optimum/graphcore/trainer_pt_utils.py
optimum/graphcore/trainer_seq2seq.py
optimum/graphcore/trainer_utils.py
optimum/graphcore/training_args.py
optimum/graphcore/training_args_seq2seq.py
optimum/graphcore/version.py
optimum/graphcore/custom_ops/__init__.py
optimum/graphcore/custom_ops/utils.py
optimum/graphcore/custom_ops/group_quantize_decompress/common.hpp
optimum/graphcore/custom_ops/group_quantize_decompress/group_quantize_decompress.cpp
optimum/graphcore/custom_ops/group_quantize_decompress/group_quantize_decompress.hpp
optimum/graphcore/custom_ops/group_quantize_decompress/group_quantize_decompress_codelet_v1.cpp
optimum/graphcore/custom_ops/group_quantize_decompress/group_quantize_decompressx.cpp
optimum/graphcore/custom_ops/group_quantize_decompress/group_quantize_decompressx.hpp
optimum/graphcore/custom_ops/sdk_version_hash/__init__.py
optimum/graphcore/custom_ops/sdk_version_hash/sdk_version_hash.py
optimum/graphcore/custom_ops/sdk_version_hash/sdk_version_hash_lib.cpp
optimum/graphcore/data/__init__.py
optimum/graphcore/data/data_collator.py
optimum/graphcore/diffusers/__init__.py
optimum/graphcore/diffusers/pipelines/__init__.py
optimum/graphcore/diffusers/pipelines/stable_diffusion/__init__.py
optimum/graphcore/diffusers/pipelines/stable_diffusion/ipu_configs.py
optimum/graphcore/diffusers/pipelines/stable_diffusion/pipeline_stable_diffusion.py
optimum/graphcore/diffusers/pipelines/stable_diffusion/pipeline_stable_diffusion_img2img.py
optimum/graphcore/diffusers/pipelines/stable_diffusion/pipeline_stable_diffusion_inpaint.py
optimum/graphcore/diffusers/pipelines/stable_diffusion/pipeline_stable_diffusion_mixin.py
optimum/graphcore/diffusers/pipelines/stable_diffusion/safety_checker.py
optimum/graphcore/generation/__init__.py
optimum/graphcore/generation/attention_mixin.py
optimum_graphcore-0.7.1.dist-info/LICENSE
optimum_graphcore-0.7.1.dist-info/METADATA
optimum_graphcore-0.7.1.dist-info/WHEEL
optimum_graphcore-0.7.1.dist-info/top_level.txt
optimum_graphcore-0.7.1.dist-info/RECORD
