Metadata-Version: 2.1
Name: optimum-graphcore
Version: 0.7.1
Summary: Optimum Library is an extension of the Hugging Face Transformers library, providing a framework to integrate third-party libraries from Hardware Partners and interface with their specific functionality.
Home-page: https://huggingface.co/hardware
Author: HuggingFace Inc. Special Ops Team
Author-email: hardware@huggingface.co
License: Apache
Keywords: transformers,quantization,pruning,training,ipu
Classifier: Development Status :: 3 - Alpha
Classifier: License :: OSI Approved :: Apache Software License
Classifier: Intended Audience :: Developers
Classifier: Intended Audience :: Education
Classifier: Intended Audience :: Science/Research
Classifier: Operating System :: OS Independent
Classifier: Programming Language :: Python :: 3.8
Classifier: Programming Language :: Python :: 3.9
Classifier: Topic :: Scientific/Engineering :: Artificial Intelligence
License-File: LICENSE
Requires-Dist: transformers (==4.29.2)
Requires-Dist: optimum (==1.6.1)
Requires-Dist: diffusers[torch] (==0.12.1)
Requires-Dist: cppimport (==22.8.2)
Requires-Dist: datasets
Requires-Dist: tokenizers
Requires-Dist: typeguard
Requires-Dist: sentencepiece
Requires-Dist: scipy
Requires-Dist: pillow
Provides-Extra: quality
Requires-Dist: black (~=23.1) ; extra == 'quality'
Requires-Dist: isort (>=5.5.4) ; extra == 'quality'
Requires-Dist: ruff (<=0.0.259,>=0.0.241) ; extra == 'quality'
Provides-Extra: testing
Requires-Dist: filelock ; extra == 'testing'
Requires-Dist: GitPython ; extra == 'testing'
Requires-Dist: parameterized ; extra == 'testing'
Requires-Dist: psutil ; extra == 'testing'
Requires-Dist: pytest ; extra == 'testing'
Requires-Dist: pytest-pythonpath ; extra == 'testing'
Requires-Dist: pytest-xdist ; extra == 'testing'
Requires-Dist: librosa ; extra == 'testing'
Requires-Dist: soundfile ; extra == 'testing'
